{
	"apps": [
		{
			"text": "NetData",
			"tip": "View server health stats",
			"icon": "img/apps/netdata.png",
			"link": "https://westroppfamily.com/monitor"
		},
		{
			"text": "transmission",
			"tip": "Manage torrents",
			"icon": "img/apps/transmission.png",
			"link": "https://westroppfamily.com/transmission"
		},
		{
			"text": "tt-rss",
			"tip": "Feed reader",
			"icon": "img/apps/ttrss.png",
			"link": "https://westroppfamily.com/rss"
		},
		{
			"text": "Wallabag",
			"tip": "Articles and web clippings",
			"icon": "img/apps/wallabag.png",
			"link": "https://westroppfamily.com/wallabag/"
		},
		{
			"text": "Syncthing",
			"tip": "File Syncing",
			"icon": "img/apps/syncthing.png",
			"link": "https://westroppfamily.com/sync/"
		},
		{
			"text": "Plex (-)",
			"tip": "Movies and TV streaming",
			"icon": "img/apps/plex.png",
			"link": "https://westroppfamily.com/plex/index.html"
		},
		{
			"text": "subsonic (-)",
			"tip": "Music streaming",
			"icon": "img/apps/subsonic.png",
			"link": "https://westroppfamily.com/music/"
		},
		{
			"text": "OwnCloud (-)",
			"tip": "Manage server files",
			"icon": "img/apps/owncloud.png",
			"link": "https://westroppfamily.com/cloud"
		},
		{
			"text": "Dokuwiki (-)",
			"tip": "Personal Wiki",
			"icon": "img/apps/dokuwiki.png",
			"link": "https://westroppfamily.com/"
		},
		{
			"text": "GitLab (-)",
			"tip": "Source Control",
			"icon": "img/apps/gitlab.png",
			"link": "https://westroppfamily.com/"
		}
	]
}